<?xml version="1.0" encoding="utf-8" ?><dwsync><file name="alert.gif" server="ftp.moradadigital.com//sitebuilder/" local="128828412000000000" remote="128828412000000000" Dst="-1" /><file name="button.gif" server="ftp.moradadigital.com//sitebuilder/" local="128828412000000000" remote="128828412000000000" Dst="-1" /><file name="buttons.gif" server="ftp.moradadigital.com//sitebuilder/" local="128828412000000000" remote="128828412000000000" Dst="-1" /><file name="confirm.gif" server="ftp.moradadigital.com//sitebuilder/" local="128828412000000000" remote="128828412000000000" Dst="-1" /><file name="corners.gif" server="ftp.moradadigital.com//sitebuilder/" local="128828412000000000" remote="128828412000000000" Dst="-1" /><file name="horizontal.gif" server="ftp.moradadigital.com//sitebuilder/" local="128828412000000000" remote="128828412000000000" Dst="-1" /><file name="vertical.gif" server="ftp.moradadigital.com//sitebuilder/" local="128828412000000000" remote="128828412000000000" Dst="-1" /><file name="alert.gif" server="ftp.boxvenue.net//sitebuilder/" local="3512442780" remote="12074788592" Dst="-1" /><file name="button.gif" server="ftp.boxvenue.net//sitebuilder/" local="3512442780" remote="12074788592" Dst="-1" /><file name="buttons.gif" server="ftp.boxvenue.net//sitebuilder/" local="3512442782" remote="12074788592" Dst="-1" /><file name="confirm.gif" server="ftp.boxvenue.net//sitebuilder/" local="3512442782" remote="12074788592" Dst="-1" /><file name="corners.gif" server="ftp.boxvenue.net//sitebuilder/" local="3512442782" remote="12074788592" Dst="-1" /><file name="horizontal.gif" server="ftp.boxvenue.net//sitebuilder/" local="3512442783" remote="12074788592" Dst="-1" /><file name="vertical.gif" server="ftp.boxvenue.net//sitebuilder/" local="3512442783" remote="12074788592" Dst="-1" /></dwsync>